CHANGELOG.md
LICENSE
entropylab/__init__.py
entropylab/cli/__init__.py
entropylab/cli/cli.md
entropylab/cli/main.py
entropylab/components/__init__.py
entropylab/components/instrument_driver.py
entropylab/components/lab_model.py
entropylab/components/lab_topology.py
entropylab/components/qcodes_adapter.py
entropylab/components/readme.md
entropylab/config.py
entropylab/conftest.py
entropylab/dashboard/__init__.py
entropylab/dashboard/app.py
entropylab/dashboard/assets/dashboard.css
entropylab/dashboard/assets/favicon.ico
entropylab/dashboard/assets/images/entropy_icon.svg
entropylab/dashboard/assets/images/entropy_logo.svg
entropylab/dashboard/assets/images/entropy_logo_dark.svg
entropylab/dashboard/assets/images/favicon.png
entropylab/dashboard/assets/images/favicon.svg
entropylab/dashboard/assets/params.css
entropylab/dashboard/pages/__init__.py
entropylab/dashboard/pages/components/__init__.py
entropylab/dashboard/pages/components/footer.py
entropylab/dashboard/pages/components/top_bar.py
entropylab/dashboard/pages/params/__init__.py
entropylab/dashboard/pages/params/callbacks.py
entropylab/dashboard/pages/params/layout.py
entropylab/dashboard/pages/params/utils.py
entropylab/dashboard/pages/results/__init__.py
entropylab/dashboard/pages/results/auto_plot.py
entropylab/dashboard/pages/results/callbacks.py
entropylab/dashboard/pages/results/dashboard_data.py
entropylab/dashboard/pages/results/layout.py
entropylab/dashboard/pages/results/table.py
entropylab/dashboard/readme.md
entropylab/dashboard/theme.py
entropylab/flame/readme.md
entropylab/logger.py
entropylab/pipeline/__init__.py
entropylab/pipeline/api/__init__.py
entropylab/pipeline/api/data_reader.py
entropylab/pipeline/api/data_writer.py
entropylab/pipeline/api/errors.py
entropylab/pipeline/api/execution.py
entropylab/pipeline/api/experiment.py
entropylab/pipeline/api/graph.py
entropylab/pipeline/api/memory_reader_writer.py
entropylab/pipeline/api/plot.py
entropylab/pipeline/graph_experiment.py
entropylab-0.15.9.dist-info/LICENSE
entropylab-0.15.9.dist-info/METADATA
entropylab-0.15.9.dist-info/WHEEL
entropylab-0.15.9.dist-info/entry_points.txt
entropylab-0.15.9.dist-info/RECORD
