Metadata-Version: 2.1
Name: entropylab
Version: 0.15.9
Summary: 
Home-page: https://github.com/entropy-lab/entropy
License: BSD-3-Clause
Author: Tal Shani
Author-email: tal@quantum-machines.co
Requires-Python: >3.7.1,<3.11
Classifier: License :: OSI Approved :: BSD License
Classifier: Programming Language :: Python :: 3
Classifier: Programming Language :: Python :: 3.8
Classifier: Programming Language :: Python :: 3.9
Classifier: Programming Language :: Python :: 3.10
Requires-Dist: alembic (>=1.6.5,<2.0.0)
Requires-Dist: bokeh (>=2.3.0,<3.0.0)
Requires-Dist: dash (>=2.4.1,<3.0.0)
Requires-Dist: dash-bootstrap-components (>=1.0.0,<2.0.0)
Requires-Dist: dill (>=0.3.3,<0.4.0)
Requires-Dist: dynaconf (>=3.1.4,<4.0.0)
Requires-Dist: fastapi (>=0.75,<0.78)
Requires-Dist: filelock (>=3.7.1,<4.0.0)
Requires-Dist: graphviz (>=0.16,<0.17)
Requires-Dist: h5py (>=3.3.0,<4.0.0)
Requires-Dist: hupper (>=1.10.3,<2.0.0)
Requires-Dist: jsonpickle (>=2.0.0,<3.0.0)
Requires-Dist: matplotlib (>=3.4.1,<4.0.0)
Requires-Dist: munch (>=2.5.0,<3.0.0)
Requires-Dist: networkx (==2.6.0)
Requires-Dist: numpy (>=1.19,<2.0)
Requires-Dist: pandas (>=1.2.3,<2.0.0)
Requires-Dist: param (>=1.10.1,<2.0.0)
Requires-Dist: psutil (>=5.9.0,<6.0.0)
Requires-Dist: pytz (>=2021.3,<2023.0)
Requires-Dist: pyzmq (>=22.3,<24.0)
Requires-Dist: qualang-tools (>=0.12.0,<0.13.0)
Requires-Dist: sqlalchemy (>=2.0.7,<3.0.0)
Requires-Dist: tinydb (>=4.5.2,<5.0.0)
Requires-Dist: waitress (>=2.1.2,<3.0.0)
